[
    {
        "name": "brand",
        "label": "Brand",
        "type": "select",
        "options": [
            "All",
            "Lenovo",
            "Avita",
            "HP",
            "acer",
            "ASUS",
            "DELL",
            "RedmiBook",
            "realme",
            "Infinix",
            "MSI",
            "MICROSOFT",
            "Smartron",
            "LG",
            "Nokia",
            "APPLE",
            "Vaio",
            "Mi",
            "ALIENWARE",
            "iball",
            "SAMSUNG"
        ]
    },
    {
        "name": "price",
        "label": "Price",
        "type": "range",
        "min": 0,
        "max": 3000
    },
    {
        "name": "ram_gb",
        "label": "Ram Size",
        "type": "select",
        "options": [
            "All",
            "4 GB GB",
            "8 GB GB",
            "16 GB GB",
            "32 GB GB"
        ]
    },
    {
        "name": "os",
        "label": "OS",
        "type": "select",
        "options": [
            "All",
            "Windows",
            "DOS",
            "Mac"
        ]
    },
    {
        "name": "processor_brand",
        "label": "Processor Brand",
        "type": "select",
        "options": [
            "All",
            "AMD",
            "Intel",
            "M1",
            "MediaTek",
            "Qualcomm"
        ]
    },
    {
        "name": "weight",
        "label": "Weight",
        "type": "select",
        "options": [
            "All",
            "ThinNlight",
            "Casual",
            "Gaming"
        ]
    }
]